{
    "version": "d57e1f8baae3680901b48eb4b421de4a7aa95cfc",
    "description": "\ud83c\udf38 A command-line fuzzy finder (git ssh clone)",
    "license": "MIT license",
    "homepage": "https://github.com/junegunn/fzf",
    "notes": "Type fzf to start",
    "url": "https://raw.githubusercontent.com/ingenarel/ingenarel-scoop-bucket/refs/heads/master/decoy/fzf-decoy",
    "hash": "d2c3cdd4a6e77920e7d0a4e0a994e16118ef061290e80535fb6857895ae305c3",
    "depends": [
        "go",
        "git"
    ],
    "pre_install": [
        "echo '' 'trying to uninstall conflicts'",
        "scoop uninstall fzf fzf-git",
        "cd $dir",
        "git clone --depth 1 --branch master git@github.com:junegunn/fzf.git",
        "echo 'building fzf...' ''",
        "cd fzf",
        "go build -ldflags '-s -w' .",
        "echo 'Removing unneeded stuff' ''",
        "cd $dir",
        "Move-Item fzf/fzf.exe fzf.exe",
        "Remove-Item -Recurse -Force fzf"
    ],
    "bin": [
        "fzf.exe"
    ],
    "conflicts": [
        "fzf",
        "fzf-git"
    ]
}