{
    "version": "dac5b6fde1cb6242492e8d27cbea162e37517be0",
    "description": "\ud83c\udf38 A command-line fuzzy finder (git ssh clone)",
    "license": "MIT license",
    "homepage": "https://github.com/junegunn/fzf",
    "notes": "Type fzf to start",
    "url": "https://raw.githubusercontent.com/ingenarel/ingenarel-scoop-bucket/refs/heads/master/decoy/fzf-decoy",
    "hash": "e7b339c6d190754164fc267b9453a933abf109e5dceb05d74d6055ec7b3be345",
    "depends": [
        "go",
        "git"
    ],
    "pre_install": [
        "echo '' 'trying to uninstall conflicts'",
        "scoop uninstall fzf fzf-git",
        "cd $dir",
        "git clone --depth 1 --branch master git@github.com:junegunn/fzf.git",
        "echo 'building fzf...' ''",
        "cd fzf",
        "go build -ldflags '-s -w' .",
        "echo 'Removing unneeded stuff' ''",
        "cd $dir",
        "Move-Item fzf/fzf.exe fzf.exe",
        "Remove-Item -Recurse -Force fzf"
    ],
    "bin": [
        "fzf.exe"
    ],
    "conflicts": [
        "fzf",
        "fzf-git"
    ]
}