{
    "version": "1b571f9e6b0a9a0040654aaf99333509a74613fc",
    "description": "Simple terminal UI for git commands (git ssh clone)",
    "license": "MIT license",
    "homepage": "https://github.com/jesseduffield/lazygit",
    "notes": "Type lazygit to start\nIt can also be used in neovim by using floatterm or the lazygit wrapper",
    "url": "https://raw.githubusercontent.com/ingenarel/ingenarel-scoop-bucket/refs/heads/master/decoy/lazygit-decoy",
    "hash": "6f34323337427b5b00f1aea4a0d3f4184c30eaecb3487f5cd4eb2b691b23c838",
    "depends": [
        "go",
        "git"
    ],
    "pre_install": [
        "echo '' 'trying to uninstall conflicts'",
        "scoop uninstall lazygit lazygit-git",
        "cd $dir",
        "git clone --depth 1 --branch master git@github.com:jesseduffield/lazygit.git",
        "echo 'building lazygit...' ''",
        "cd lazygit",
        "go build -ldflags '-s -w' .",
        "echo 'Removing unneeded stuff' ''",
        "cd $dir",
        "Move-Item lazygit/lazygit.exe lazygit.exe",
        "Remove-Item -Recurse -Force lazygit"
    ],
    "bin": [
        "lazygit.exe"
    ],
    "conflicts": [
        "lazygit",
        "lazygit-git"
    ]
}