{
    "version": "55236802c3faedf3d3133bbaaceecee39fb6e8c1",
    "description": "Simple terminal UI for git commands (git ssh clone)",
    "license": "MIT license",
    "homepage": "https://github.com/jesseduffield/lazygit",
    "notes": "Type lazygit to start\nIt can also be used in neovim by using floatterm or the lazygit wrapper",
    "url": "https://raw.githubusercontent.com/ingenarel/ingenarel-scoop-bucket/refs/heads/master/decoy/lazygit-decoy",
    "hash": "7b0e50d83048516f4ba10263c51f8c6b8104d3c8d517997276111859e66021d0",
    "depends": [
        "go",
        "git"
    ],
    "pre_install": [
        "echo '' 'trying to uninstall conflicts'",
        "scoop uninstall lazygit lazygit-git",
        "cd $dir",
        "git clone --depth 1 --branch master git@github.com:jesseduffield/lazygit.git",
        "echo 'building lazygit...' ''",
        "cd lazygit",
        "go build -ldflags '-s -w' .",
        "echo 'Removing unneeded stuff' ''",
        "cd $dir",
        "Move-Item lazygit/lazygit.exe lazygit.exe",
        "Remove-Item -Recurse -Force lazygit"
    ],
    "bin": [
        "lazygit.exe"
    ],
    "conflicts": [
        "lazygit",
        "lazygit-git"
    ]
}